odoo8_addon_l10n_es_aeat_vat_prorrate_asset-8.0.1.0.1-py2.7-nspkg.pth
odoo8_addon_l10n_es_aeat_vat_prorrate_asset-8.0.1.0.1.dist-info/DESCRIPTION.rst
odoo8_addon_l10n_es_aeat_vat_prorrate_asset-8.0.1.0.1.dist-info/METADATA
odoo8_addon_l10n_es_aeat_vat_prorrate_asset-8.0.1.0.1.dist-info/RECORD
odoo8_addon_l10n_es_aeat_vat_prorrate_asset-8.0.1.0.1.dist-info/WHEEL
odoo8_addon_l10n_es_aeat_vat_prorrate_asset-8.0.1.0.1.dist-info/metadata.json
odoo8_addon_l10n_es_aeat_vat_prorrate_asset-8.0.1.0.1.dist-info/namespace_packages.txt
odoo8_addon_l10n_es_aeat_vat_prorrate_asset-8.0.1.0.1.dist-info/top_level.txt
odoo_addons/l10n_es_aeat_vat_prorrate_asset/README.rst
odoo_addons/l10n_es_aeat_vat_prorrate_asset/__init__.py
odoo_addons/l10n_es_aeat_vat_prorrate_asset/__openerp__.py
odoo_addons/l10n_es_aeat_vat_prorrate_asset/i18n/ca.po
odoo_addons/l10n_es_aeat_vat_prorrate_asset/i18n/cs.po
odoo_addons/l10n_es_aeat_vat_prorrate_asset/i18n/es.po
odoo_addons/l10n_es_aeat_vat_prorrate_asset/i18n/es_CO.po
odoo_addons/l10n_es_aeat_vat_prorrate_asset/i18n/es_CR.po
odoo_addons/l10n_es_aeat_vat_prorrate_asset/i18n/fr.po
odoo_addons/l10n_es_aeat_vat_prorrate_asset/i18n/gl.po
odoo_addons/l10n_es_aeat_vat_prorrate_asset/i18n/hr.po
odoo_addons/l10n_es_aeat_vat_prorrate_asset/i18n/nl.po
odoo_addons/l10n_es_aeat_vat_prorrate_asset/i18n/pl.po
odoo_addons/l10n_es_aeat_vat_prorrate_asset/i18n/pt.po
odoo_addons/l10n_es_aeat_vat_prorrate_asset/i18n/pt_BR.po
odoo_addons/l10n_es_aeat_vat_prorrate_asset/i18n/ru.po
odoo_addons/l10n_es_aeat_vat_prorrate_asset/i18n/sl.po
odoo_addons/l10n_es_aeat_vat_prorrate_asset/i18n/sv.po
odoo_addons/l10n_es_aeat_vat_prorrate_asset/i18n/tr.po
odoo_addons/l10n_es_aeat_vat_prorrate_asset/i18n/vi.po
odoo_addons/l10n_es_aeat_vat_prorrate_asset/models/__init__.py
odoo_addons/l10n_es_aeat_vat_prorrate_asset/models/account_asset_asset.py
odoo_addons/l10n_es_aeat_vat_prorrate_asset/models/account_invoice.py
odoo_addons/l10n_es_aeat_vat_prorrate_asset/models/mod303.py
odoo_addons/l10n_es_aeat_vat_prorrate_asset/static/description/icon.png
odoo_addons/l10n_es_aeat_vat_prorrate_asset/static/description/icon_source.svg
odoo_addons/l10n_es_aeat_vat_prorrate_asset/views/account_asset_asset_view.xml
odoo_addons/l10n_es_aeat_vat_prorrate_asset/views/account_invoice_view.xml
