Metadata-Version: 2.0
Name: odoo8-addon-l10n-es-aeat-vat-prorrate-asset
Version: 8.0.1.0.1
Summary: AEAT - Prorrata de IVA - Extensión para los activos
Home-page: https://www.tecnativa.com
Author: Tecnativa, Odoo Community Association (OCA)
Author-email: support@odoo-community.org
License: AGPL-3
Platform: UNKNOWN
Classifier: Programming Language :: Python :: 2.7
Classifier: Framework :: Odoo
Classifier: License :: OSI Approved :: GNU Affero General Public License v3
Requires-Dist: odoo (<9.0a,>=8.0a)
Requires-Dist: odoo8-addon-l10n-es-aeat-vat-prorrate
